termlit/__init__.py
termlit/cli.py
termlit/runtime.py
termlit/session.py
termlit/ssh_server_plain.py
termlit/start_services.py
termlit/telnet_server.py
termlit-0.3.1.dist-info/licenses/LICENSE
termlit-0.3.1.dist-info/METADATA
termlit-0.3.1.dist-info/WHEEL
termlit-0.3.1.dist-info/entry_points.txt
termlit-0.3.1.dist-info/top_level.txt
termlit-0.3.1.dist-info/RECORD
