Metadata-Version: 2.4
Name: termlit
Version: 0.3.1
Summary: Termlit is a small Python tool that provides an SSH server interface. It makes it easy to expose interactive applications over SSH — for example, to host AI-powered conversational services that users can connect to with an SSH client.
Author-email: stoday <stoday@gmail.com>
License: MIT
Project-URL: Homepage, https://stoday.github.io/termlit
Project-URL: source, https://github.com/stoday/termlit
Project-URL: Documentation, https://github.com/stoday/termlit#readme
Project-URL: BugTracker, https://github.com/stoday/termlit/issues
Classifier: License :: OSI Approved :: MIT License
Classifier: Programming Language :: Python :: 3
Classifier: Programming Language :: Python :: 3 :: Only
Classifier: Programming Language :: Python :: 3.10
Requires-Python: >=3.10
License-File: LICENSE
Requires-Dist: paramiko>=4.0.0
Requires-Dist: requests>=2.32.5
Requires-Dist: rich>=14.2.0
Dynamic: license-file
